{
  "cart": [
    {
      "id": "1",
      "name": "일반 상품1",
      "price": 8500,
      "originalPrice": 12000,
      "quantity": 1,
      "type": "subscription",
      "image": "https://www.lrt.lt/img/2022/02/09/1191080-981331-1287x836.jpg"
    },
    {
      "id": "2",
      "name": "유기농 사과",
      "price": 15000,
      "originalPrice": 18000,
      "quantity": 3,
      "type": "regular",
      "image": "https://www.lrt.lt/img/2022/02/09/1191080-981331-1287x836.jpg"
    },
    {
      "id": "3",
      "name": "무농약 바나나",
      "price": 6000,
      "originalPrice": 7500,
      "quantity": 1,
      "type": "subscription",
      "image": "https://www.lrt.lt/img/2022/02/09/1191080-981331-1287x836.jpg"
    },
    {
      "id": "4",
      "name": "친환경 당근",
      "price": 4000,
      "originalPrice": 5000,
      "quantity": 5,
      "type": "regular",
      "image": "https://www.lrt.lt/img/2022/02/09/1191080-981331-1287x836.jpg"
    }
  ],
  "delivery": {
    "address": "",
    "isRegistered": false
  },
  "user": {
    "id": 1,
    "name": "홍길동",
    "email": "hong@example.com"
  },
  "products": [
    {
      "product_id": 1,
      "product_detail_category_id": "과일",
      "sales_type_id": 0,
      "customer_id": 1,
      "product_name": "유기농 아보카도",
      "product_description": "신선하고 맛있는 유기농 아보카도입니다.",
      "product_image": "https://www.lrt.lt/img/2022/02/09/1191080-981331-1287x836.jpg",
      "product_price": 2500,
      "product_origin": "멕시코",
      "base_discount_rate": 0,
      "regular_discount_rate": 5,
      "personalize_discount_rate": 0,
      "is_page_visibility": true,
      "is_regular_sale": true,
      "id": "6745"
    },
    {
      "product_id": 2,
      "product_detail_category_id": "채소",
      "sales_type_id": 0,
      "customer_id": 1,
      "product_name": "국내산 무농약 콩나물",
      "product_description": "깨끗하고 안전한 국내산 무농약 콩나물입니다.",
      "product_image": "https://www.lrt.lt/img/2022/02/09/1191080-981331-1287x836.jpg",
      "product_price": 1000,
      "product_origin": "대한민국",
      "base_discount_rate": 0,
      "regular_discount_rate": 0,
      "personalize_discount_rate": 10,
      "is_page_visibility": true,
      "is_regular_sale": false,
      "id": "e6d6"
    },
    {
      "product_id": 3,
      "product_detail_category_id": "쌀",
      "sales_type_id": 0,
      "customer_id": 1,
      "product_name": "찰진 현미 1kg",
      "product_description": "맛과 영양이 풍부한 찰진 현미입니다.",
      "product_image": "https://www.lrt.lt/img/2022/02/09/1191080-981331-1287x836.jpg",
      "product_price": 5000,
      "product_origin": "대한민국",
      "base_discount_rate": 10,
      "regular_discount_rate": 0,
      "personalize_discount_rate": 0,
      "is_page_visibility": false,
      "is_regular_sale": false,
      "id": "485b"
    },
    {
      "product_id": 4,
      "product_detail_category_id": "계란",
      "sales_type_id": 0,
      "customer_id": 2,
      "product_name": "1등급 한우 등심",
      "product_description": "신선하고 맛있는 1등급 한우 등심입니다.",
      "product_image": "https://www.lrt.lt/img/2022/02/09/1191080-981331-1287x836.jpg",
      "product_price": 35000,
      "product_origin": "대한민국",
      "base_discount_rate": 0,
      "regular_discount_rate": 15,
      "personalize_discount_rate": 0,
      "is_page_visibility": true,
      "is_regular_sale": true,
      "id": "a9d0"
    },
    {
      "product_id": 5,
      "product_detail_category_id": "수산물",
      "sales_type_id": 0,
      "customer_id": 3,
      "product_name": "손질된 노르웨이 고등어",
      "product_description": "신선하고 맛있는 손질된 노르웨이 고등어입니다.",
      "product_image": "https://www.lrt.lt/img/2022/02/09/1191080-981331-1287x836.jpg",
      "product_price": 8000,
      "product_origin": "노르웨이",
      "base_discount_rate": 0,
      "regular_discount_rate": 0,
      "personalize_discount_rate": 5,
      "is_page_visibility": true,
      "is_regular_sale": false,
      "id": "f041"
    },
    {
      "product_id": 6,
      "product_detail_category_id": "김치",
      "sales_type_id": 0,
      "customer_id": 3,
      "product_name": "종가집 포기김치",
      "product_description": "맛있는 종가집 포기김치입니다.",
      "product_image": "https://www.lrt.lt/img/2022/02/09/1191080-981331-1287x836.jpg",
      "product_price": 12000,
      "product_origin": "대한민국",
      "base_discount_rate": 5,
      "regular_discount_rate": 0,
      "personalize_discount_rate": 0,
      "is_page_visibility": false,
      "is_regular_sale": false,
      "id": "8482"
    },
    {
      "product_id": 7,
      "product_detail_category_id": "우유",
      "sales_type_id": 0,
      "customer_id": 4,
      "product_name": "파스퇴르 저지방 우유",
      "product_description": "신선하고 건강한 파스퇴르 저지방 우유입니다.",
      "product_image": "https://www.lrt.lt/img/2022/02/09/1191080-981331-1287x836.jpg",
      "product_price": 3000,
      "product_origin": "대한민국",
      "base_discount_rate": 0,
      "regular_discount_rate": 10,
      "personalize_discount_rate": 0,
      "is_page_visibility": true,
      "is_regular_sale": true,
      "id": "afdb"
    },
    {
      "product_id": 8,
      "product_detail_category_id": "고추장",
      "sales_type_id": 0,
      "customer_id": 5,
      "product_name": "오뚜기 진라면 순한맛",
      "product_description": "얼큰하고 맛있는 오뚜기 진라면 순한맛입니다.",
      "product_image": "https://www.lrt.lt/img/2022/02/09/1191080-981331-1287x836.jpg",
      "product_price": 800,
      "product_origin": "대한민국",
      "base_discount_rate": 0,
      "regular_discount_rate": 0,
      "personalize_discount_rate": 8,
      "is_page_visibility": true,
      "is_regular_sale": false,
      "id": "db9f"
    },
    {
      "product_id": 9,
      "product_detail_category_id": "과일",
      "sales_type_id": 0,
      "customer_id": 6,
      "product_name": "하이트 진로 참이슬",
      "product_description": "깔끔한 맛의 하이트 진로 참이슬입니다.",
      "product_image": "https://www.lrt.lt/img/2022/02/09/1191080-981331-1287x836.jpg",
      "product_price": 1500,
      "product_origin": "대한민국",
      "base_discount_rate": 7,
      "regular_discount_rate": 0,
      "personalize_discount_rate": 0,
      "is_page_visibility": false,
      "is_regular_sale": false,
      "id": "d4bd"
    },
    {
      "product_id": 10,
      "product_detail_category_id": "채소",
      "sales_type_id": 0,
      "customer_id": 7,
      "product_name": "제주 삼다수 2L",
      "product_description": "깨끗하고 시원한 제주 삼다수입니다.",
      "product_image": "https://www.lrt.lt/img/2022/02/09/1191080-981331-1287x836.jpg",
      "product_price": 1200,
      "product_origin": "대한민국",
      "base_discount_rate": 0,
      "regular_discount_rate": 5,
      "personalize_discount_rate": 0,
      "is_page_visibility": true,
      "is_regular_sale": true,
      "id": "15e9"
    }
  ]
}
